rytrading/__init__.py
rytrading/upload_s3.py
rytrading-0.0.3.dist-info/METADATA
rytrading-0.0.3.dist-info/WHEEL
rytrading-0.0.3.dist-info/top_level.txt
rytrading-0.0.3.dist-info/RECORD
